bunumber/__init__.py
bunumber/numdigit.py
bunumber/numletter.py
bunumber-0.0.1.dist-info/WHEEL
bunumber-0.0.1.dist-info/METADATA
bunumber-0.0.1.dist-info/RECORD
